odoo10_addon_web_editor_background_color-10.0.1.0.0-py2.7-nspkg.pth
odoo/addons/web_editor_background_color/README.rst
odoo/addons/web_editor_background_color/__init__.py
odoo/addons/web_editor_background_color/__manifest__.py
odoo/addons/web_editor_background_color/i18n/ca.po
odoo/addons/web_editor_background_color/i18n/es.po
odoo/addons/web_editor_background_color/i18n/fr.po
odoo/addons/web_editor_background_color/i18n/sl.po
odoo/addons/web_editor_background_color/static/description/icon.png
odoo/addons/web_editor_background_color/static/description/mass_mailing_editor.png
odoo/addons/web_editor_background_color/static/src/css/background_color.less
odoo/addons/web_editor_background_color/static/src/js/background_color.js
odoo/addons/web_editor_background_color/static/src/lib/bootstrap-colorpicker/alpha-horizontal.png
odoo/addons/web_editor_background_color/static/src/lib/bootstrap-colorpicker/alpha.png
odoo/addons/web_editor_background_color/static/src/lib/bootstrap-colorpicker/bootstrap-colorpicker.js
odoo/addons/web_editor_background_color/static/src/lib/bootstrap-colorpicker/colorpicker.less
odoo/addons/web_editor_background_color/static/src/lib/bootstrap-colorpicker/hue-horizontal.png
odoo/addons/web_editor_background_color/static/src/lib/bootstrap-colorpicker/hue.png
odoo/addons/web_editor_background_color/static/src/lib/bootstrap-colorpicker/saturation.png
odoo/addons/web_editor_background_color/static/src/xml/colorpicker.xml
odoo/addons/web_editor_background_color/templates/assets.xml
odoo10_addon_web_editor_background_color-10.0.1.0.0.dist-info/DESCRIPTION.rst
odoo10_addon_web_editor_background_color-10.0.1.0.0.dist-info/METADATA
odoo10_addon_web_editor_background_color-10.0.1.0.0.dist-info/RECORD
odoo10_addon_web_editor_background_color-10.0.1.0.0.dist-info/WHEEL
odoo10_addon_web_editor_background_color-10.0.1.0.0.dist-info/metadata.json
odoo10_addon_web_editor_background_color-10.0.1.0.0.dist-info/namespace_packages.txt
odoo10_addon_web_editor_background_color-10.0.1.0.0.dist-info/top_level.txt
