Metadata-Version: 2.0
Name: odoo10-addon-web-editor-background-color
Version: 10.0.1.0.0
Summary: Set any background color for web editor snippets
Home-page: https://www.tecnativa.com
Author: Tecnativa, Odoo Community Association (OCA)
Author-email: support@odoo-community.org
License: LGPL-3
Platform: UNKNOWN
Classifier: Programming Language :: Python :: 2.7
Classifier: Framework :: Odoo
Classifier: License :: OSI Approved :: GNU Lesser General Public License v3 (LGPLv3)
Requires-Dist: odoo (<10.1dev,>=10.0)
